wgdtree/__init__.py
wgdtree/batch_run.py
wgdtree/retention_rates.py
wgdtree/rooting.py
wgdtree/simulation.py
wgdtree/split.py
wgdtree-1.0.dist-info/LICENSE
wgdtree-1.0.dist-info/METADATA
wgdtree-1.0.dist-info/WHEEL
wgdtree-1.0.dist-info/top_level.txt
wgdtree-1.0.dist-info/RECORD
