Metadata-Version: 2.1
Name: wgdtree
Version: 1.0
Summary: A small package for simulating and analysing phylo-genetic trees.
Home-page: https://github.com/cnickh/wgdtree
Author: Charles Henry
Author-email: Charlesnhenry@gmail.com
Project-URL: Bug Tracker, https://github.com/cnickh/wgdtree/issues
Classifier: Programming Language :: Python :: 3
Classifier: License :: OSI Approved :: MIT License
Classifier: Operating System :: OS Independent
Requires-Python: >=3.7
License-File: LICENSE
